stocksignals/__init__.py
stocksignals/bbands.py
stocksignals/calc_moving_avg.py
stocksignals/data/FFIE.csv
stocksignals/data/MSFT.csv
stocksignals/get_data.py
stocksignals/plot_bbands.py
stocksignals/plot_ma_10_20.py
stocksignals/plot_ma_200days.py
stocksignals-0.0.7.dist-info/METADATA
stocksignals-0.0.7.dist-info/WHEEL
stocksignals-0.0.7.dist-info/LICENSE
stocksignals-0.0.7.dist-info/RECORD
