Metadata-Version: 2.1
Name: stocksignals
Version: 0.0.7
Summary: Calculate buy/sell signal indicators for a stock!
Home-page: https://github.com/UBC-MDS/StockSignals
License: MIT
Author: Ruslan Dimitrov, Robin Dhilon, Peng Zhang, Chenyang Wang
Requires-Python: >=3.9,<4.0
Classifier: License :: OSI Approved :: MIT License
Classifier: Programming Language :: Python :: 3
Classifier: Programming Language :: Python :: 3.9
Classifier: Programming Language :: Python :: 3.10
Classifier: Programming Language :: Python :: 3.11
Requires-Dist: matplotlib (>=3.6.3,<4.0.0)
Requires-Dist: pandas (>=1.5.3,<2.0.0)
Requires-Dist: yfinance (>=0.2.9,<0.3.0)
Project-URL: Documentation, https://StockSignals.readthedocs.io
Project-URL: Repository, https://github.com/UBC-MDS/StockSignals
